python_to_json/__init__.py
python_to_json/mixins.py
python_to_json-1.0.1.dist-info/DESCRIPTION.rst
python_to_json-1.0.1.dist-info/METADATA
python_to_json-1.0.1.dist-info/RECORD
python_to_json-1.0.1.dist-info/WHEEL
python_to_json-1.0.1.dist-info/metadata.json
python_to_json-1.0.1.dist-info/top_level.txt
